ais/__init__.py
ais/__main__.py
ais/core.py
ais/status.py
ais/client/__init__.py
ais/client/abstract.py
ais/client/chatgpt.py
ais/config/__init__.py
ais/config/config.py
ais/console/__init__.py
ais/console/console.py
ais/console/parser.py
ais/history/__init__.py
ais/history/history.py
ais/request/__init__.py
ais/request/request.py
ais/response/__init__.py
ais/response/response.py
ais/utils/__init__.py
ais/utils/config.py
ais/utils/console.py
ais/utils/prompt.py
ais_cli-0.2.0.dist-info/LICENSE
ais_cli-0.2.0.dist-info/METADATA
ais_cli-0.2.0.dist-info/WHEEL
ais_cli-0.2.0.dist-info/entry_points.txt
ais_cli-0.2.0.dist-info/top_level.txt
ais_cli-0.2.0.dist-info/RECORD
