Metadata-Version: 2.1
Name: ais-cli
Version: 0.2.0
Summary: Ais (ai shell) is interactive command line ai tool powered by ChatGPT (GPT-3.5)
Author: Sinan Kanidağlı
Author-email: sinan_kanidagli@hotmail.com
License: MIT
Project-URL: GitHub, https://github.com/knid/ais
Project-URL: Twitter, https://twitter.com/devknid
Project-URL: Documentation, https://github.com/knid/ais/README.md
Classifier: Development Status :: 5 - Production/Stable
Classifier: Programming Language :: Python
Classifier: Programming Language :: Python :: 3 :: Only
Classifier: Environment :: Console
Classifier: Intended Audience :: Developers
Classifier: Intended Audience :: System Administrators
Classifier: License :: OSI Approved :: MIT License
Classifier: Topic :: Software Development
Classifier: Topic :: System :: Networking
Classifier: Topic :: Terminals
Classifier: Topic :: Text Processing
Classifier: Topic :: Utilities
Requires-Python: >=3.7
License-File: LICENSE
Requires-Dist: questionary (==1.10.0)
Requires-Dist: requests (==2.28.2)
Requires-Dist: rich (==13.3.3)
Requires-Dist: setuptools
Provides-Extra: dev
Requires-Dist: pytest ; extra == 'dev'
Requires-Dist: flake8 ; extra == 'dev'
Requires-Dist: pyyaml ; extra == 'dev'
Requires-Dist: twine ; extra == 'dev'
Requires-Dist: wheel ; extra == 'dev'
Provides-Extra: test
Requires-Dist: pytest ; extra == 'test'
